registerBank.v
module registerBank (
    input wire clk,
    input wire we,
    input wire [2:0] write_addr,
    input wire [2:0] read_addr,
    input wire [7:0] write_data,
    output reg [7:0] read_data
);

    // Banco de 8 registros de 8 bits
    reg [7:0] registers [0:7];

    // Escritura síncrona
    //Se activa solo en el flanco de subida del reloj.
    always @(posedge clk) begin
        if (we) //si we esta actuvo(1)
            registers[write_addr] <= write_data;
    end

    always @(*) begin
        read_data = registers[read_addr];
    end

endmodule

registerBank_tb.v
`timescale 1ns/1ps
`include "registerBank.v"

module registerBank_tb;
    reg clk;
    reg we;
    reg [2:0] write_addr;
    reg [2:0] read_addr;
    reg [7:0] write_data;
    wire [7:0] read_data;

    registerBank uut (
        .clk(clk),
        .we(we),
        .write_addr(write_addr),
        .read_addr(read_addr),
        .write_data(write_data),
        .read_data(read_data)
    );

    // Generación de reloj
    always #5 clk = ~clk;

    initial begin
        $dumpfile("registerBank.vcd");
        $dumpvars(0, registerBank_tb);
 
        clk = 0;
        we = 0;
        write_addr = 0;
        read_addr = 0;
        write_data = 0;
        #10;

        // Escribir en registro 3
        we = 1;
        write_addr = 3;
        write_data = 8'hAA;
        #10;

        // Leer registro 3
        we = 0;
        read_addr = 3;
        #10;

        // Intentar escribir sin WE
        // no deberia escribirse
        we = 0;
        write_addr = 5;
        write_data = 8'h55;
        #10;

        // Leer registro 5 (debe ser 0)
        read_addr = 5;
        #10;

        // Escribir de vuelta en registro 5 con WE
        // si deberia escribirse
        we = 1;
        write_addr = 5;
        write_data = 8'h55;
        #10;

        // Leer registro 5 (debe ser 55)
        we = 0;
        read_addr = 5;
        #10;

        // Leer y Escribir un mismo registro
        we = 1;
        read_addr = 5;
        write_addr = 5;
        write_data = 8'hA3;
        #10;

        $finish;
    end

endmodule

registerBank.vcd
$date
	Sun Aug 31 12:43:22 2025
$end
$version
	Icarus Verilog
$end
$timescale
	1ps
$end
$scope module registerBank_tb $end
$var wire 8 ! read_data [7:0] $end
$var reg 1 " clk $end
$var reg 3 # read_addr [2:0] $end
$var reg 1 $ we $end
$var reg 3 % write_addr [2:0] $end
$var reg 8 & write_data [7:0] $end
$scope module uut $end
$var wire 1 " clk $end
$var wire 3 ' read_addr [2:0] $end
$var wire 1 $ we $end
$var wire 3 ( write_addr [2:0] $end
$var wire 8 ) write_data [7:0] $end
$var reg 8 * read_data [7:0] $end
$upscope $end
$upscope $end
$enddefinitions $end
$comment Show the parameter values. $end
$dumpall
$end
#0
$dumpvars
bx *
b0 )
b0 (
b0 '
b0 &
b0 %
0$
b0 #
0"
bx !
$end
#5000
1"
#10000
0"
b10101010 &
b10101010 )
b11 %
b11 (
1$
#15000
1"
#20000
b10101010 !
b10101010 *
0"
b11 #
b11 '
0$
#25000
1"
#30000
0"
b1010101 &
b1010101 )
b101 %
b101 (
#35000
1"
#40000
bx !
bx *
0"
b101 #
b101 '
#45000
1"
#50000
0"
1$
#55000
b1010101 !
b1010101 *
1"
#60000
0"
0$
#65000
1"
#70000
0"
b10100011 &
b10100011 )
1$
#75000
b10100011 !
b10100011 *
1"
